MANIFEST.in
README
setup.py
bin/txlb.tac
doc/architecture.txt
doc/config.dtd
doc/configure.txt
doc/scenarios.txt
doc/schedulers.txt
doc/webapi.txt
doc/xmlreference.txt
txLoadBalancer.egg-info/PKG-INFO
txLoadBalancer.egg-info/SOURCES.txt
txLoadBalancer.egg-info/dependency_links.txt
txLoadBalancer.egg-info/not-zip-safe
txLoadBalancer.egg-info/top_level.txt
txlb/__init__.py
txlb/config.py
txlb/logging.py
txlb/manager.py
txlb/model.py
txlb/proxy.py
txlb/schedulers.py
txlb/util.py
txlb/admin/__init__.py
txlb/admin/auth.py
txlb/admin/css.py
txlb/admin/pages.py
txlb/admin/template.py
txlb/application/__init__.py
txlb/application/director.py
txlb/application/service.py
txlb/test/__init__.py
txlb/test/test_manager.py
txlb/test/test_model.py
txlb/test/test_schedulers.py
txlb/test/test_util.py