Metadata-Version: 1.0
Name: txLoadBalancer
Version: 1.1.0
Summary: txLoadBalancer - A Twisted-based TCP load balancer.
Home-page: https://launchpad.net/txloadbalancer
Author: Duncan McGreggor, Anthony Baxter
Author-email: oubiwann@divmod.com
License: MIT
Platform: UNKNOWN
Classifier: Development Status :: 5 - Production/Stable
Classifier: Environment :: Web Environment
Classifier: Environment :: No Input/Output (Daemon)
Classifier: License :: OSI Approved :: Python Software Foundation License
Classifier: Operating System :: POSIX
Classifier: Operating System :: MacOS :: MacOS X
Classifier: Operating System :: Microsoft
Classifier: Programming Language :: Python
Classifier: Intended Audience :: System Administrators
Classifier: Intended Audience :: Developers
Classifier: Topic :: Internet
Classifier: Topic :: System :: Networking
